{"filename":"D:\\github\\riniga\\Azure-Website\\AzureWebsite.Nodejs\\__azurite_db_blob__.json","collections":[{"name":"$SERVICES_COLLECTION$","data":[],"idIndex":null,"binaryIndices":{},"constraints":null,"uniqueNames":["accountName"],"transforms":{},"objType":"$SERVICES_COLLECTION$","dirty":false,"cachedIndex":null,"cachedBinaryIndex":null,"cachedData":null,"adaptiveBinaryIndices":true,"transactional":false,"cloneObjects":false,"cloneMethod":"parse-stringify","asyncListeners":false,"disableMeta":false,"disableChangesApi":true,"disableDeltaChangesApi":true,"autoupdate":false,"serializableIndices":true,"disableFreeze":true,"ttl":null,"maxId":0,"DynamicViews":[],"events":{"insert":[],"update":[],"pre-insert":[],"pre-update":[],"close":[],"flushbuffer":[],"error":[],"delete":[null],"warning":[null]},"changes":[],"dirtyIds":[]},{"name":"$CONTAINERS_COLLECTION$","data":[{"accountName":"devstoreaccount1","name":"azure-webjobs-hosts","properties":{"etag":"\"0x22CF7409EB9F120\"","lastModified":"2021-10-11T18:33:35.736Z","leaseStatus":"unlocked","leaseState":"available","hasImmutabilityPolicy":false,"hasLegalHold":false},"meta":{"revision":0,"created":1633977215740,"version":0},"$loki":1},{"accountName":"devstoreaccount1","name":"images","properties":{"etag":"\"0x1AF84E2E4D61A50\"","lastModified":"2021-10-11T19:02:26.643Z","leaseStatus":"unlocked","leaseState":"available","publicAccess":"blob","hasImmutabilityPolicy":false,"hasLegalHold":false},"meta":{"revision":1,"created":1633977496729,"version":0,"updated":1633978946647},"$loki":2,"containerAcl":[]}],"idIndex":null,"binaryIndices":{"accountName":{"name":"accountName","dirty":false,"values":[1,0]},"name":{"name":"name","dirty":false,"values":[0,1]}},"constraints":null,"uniqueNames":[],"transforms":{},"objType":"$CONTAINERS_COLLECTION$","dirty":false,"cachedIndex":null,"cachedBinaryIndex":null,"cachedData":null,"adaptiveBinaryIndices":true,"transactional":false,"cloneObjects":false,"cloneMethod":"parse-stringify","asyncListeners":false,"disableMeta":false,"disableChangesApi":true,"disableDeltaChangesApi":true,"autoupdate":false,"serializableIndices":true,"disableFreeze":true,"ttl":null,"maxId":2,"DynamicViews":[],"events":{"insert":[],"update":[],"pre-insert":[],"pre-update":[],"close":[],"flushbuffer":[],"error":[],"delete":[null],"warning":[null]},"changes":[],"dirtyIds":[]},{"name":"$BLOBS_COLLECTION$","data":[{"deleted":false,"metadata":{"FunctionInstance":"000000000000000000000000652DDD82"},"accountName":"devstoreaccount1","containerName":"azure-webjobs-hosts","name":"locks/sehp5cg832817q-1192943604/host","properties":{"creationTime":"2021-10-11T18:33:35.745Z","lastModified":"2021-10-12T08:17:59.771Z","etag":"\"0x1FA3EB7A092FED0\"","contentLength":0,"contentType":"application/octet-stream","contentMD5":{"type":"Buffer","data":[212,29,140,217,143,0,178,4,233,128,9,152,236,248,66,126]},"blobType":"BlockBlob","leaseStatus":"unlocked","leaseState":"available","serverEncrypted":true,"accessTier":"Hot","accessTierInferred":true,"accessTierChangeTime":"2021-10-11T18:33:35.745Z"},"snapshot":"","isCommitted":true,"persistency":{"id":"f24d1d51-6c18-42ab-b3fa-bc7fa4768ad8","offset":0,"count":0},"meta":{"revision":3298,"created":1633977215753,"version":0,"updated":1634026692346},"$loki":1},{"accountName":"devstoreaccount1","containerName":"images","name":"BlackBishop.png","properties":{"creationTime":"2021-10-11T18:57:08.140Z","lastModified":"2021-10-11T18:57:08.140Z","etag":"\"0x1D1FD4BDB771010\"","contentLength":10003,"contentType":"image/jpg","contentMD5":{"type":"Buffer","data":[13,121,88,208,39,37,19,101,101,155,233,147,64,215,195,117]},"blobType":"BlockBlob","leaseStatus":"unlocked","leaseState":"available","serverEncrypted":true,"accessTier":"Hot","accessTierInferred":true,"accessTierChangeTime":"2021-10-11T18:57:08.140Z"},"snapshot":"","isCommitted":true,"persistency":{"id":"f24d1d51-6c18-42ab-b3fa-bc7fa4768ad8","offset":10003,"count":10003},"meta":{"revision":0,"created":1633978628147,"version":0},"$loki":3},{"accountName":"devstoreaccount1","containerName":"images","name":"BlackKing.png","properties":{"creationTime":"2021-10-12T05:03:02.884Z","lastModified":"2021-10-12T05:03:02.884Z","etag":"\"0x1B0C6D712C4AE80\"","contentLength":15983,"contentType":"image/jpg","contentMD5":{"type":"Buffer","data":[80,215,43,227,102,99,191,239,79,49,154,31,16,33,160,50]},"blobType":"BlockBlob","leaseStatus":"unlocked","leaseState":"available","serverEncrypted":true,"accessTier":"Hot","accessTierInferred":true,"accessTierChangeTime":"2021-10-12T05:03:02.884Z"},"snapshot":"","isCommitted":true,"persistency":{"id":"f24d1d51-6c18-42ab-b3fa-bc7fa4768ad8","offset":20006,"count":15983},"meta":{"revision":0,"created":1634014982893,"version":0},"$loki":4}],"idIndex":[1,3,4],"binaryIndices":{"accountName":{"name":"accountName","dirty":false,"values":[0,2,1]},"containerName":{"name":"containerName","dirty":false,"values":[0,2,1]},"name":{"name":"name","dirty":false,"values":[1,2,0]},"snapshot":{"name":"snapshot","dirty":false,"values":[0,2,1]}},"constraints":null,"uniqueNames":[],"transforms":{},"objType":"$BLOBS_COLLECTION$","dirty":false,"cachedIndex":null,"cachedBinaryIndex":null,"cachedData":null,"adaptiveBinaryIndices":true,"transactional":false,"cloneObjects":false,"cloneMethod":"parse-stringify","asyncListeners":false,"disableMeta":false,"disableChangesApi":true,"disableDeltaChangesApi":true,"autoupdate":false,"serializableIndices":true,"disableFreeze":true,"ttl":null,"maxId":4,"DynamicViews":[],"events":{"insert":[],"update":[],"pre-insert":[],"pre-update":[],"close":[],"flushbuffer":[],"error":[],"delete":[null],"warning":[null]},"changes":[],"dirtyIds":[]},{"name":"$BLOCKS_COLLECTION$","data":[],"idIndex":null,"binaryIndices":{"accountName":{"name":"accountName","dirty":false,"values":[]},"containerName":{"name":"containerName","dirty":false,"values":[]},"blobName":{"name":"blobName","dirty":false,"values":[]},"name":{"name":"name","dirty":false,"values":[]}},"constraints":null,"uniqueNames":[],"transforms":{},"objType":"$BLOCKS_COLLECTION$","dirty":false,"cachedIndex":null,"cachedBinaryIndex":null,"cachedData":null,"adaptiveBinaryIndices":true,"transactional":false,"cloneObjects":false,"cloneMethod":"parse-stringify","asyncListeners":false,"disableMeta":false,"disableChangesApi":true,"disableDeltaChangesApi":true,"autoupdate":false,"serializableIndices":true,"disableFreeze":true,"ttl":null,"maxId":0,"DynamicViews":[],"events":{"insert":[],"update":[],"pre-insert":[],"pre-update":[],"close":[],"flushbuffer":[],"error":[],"delete":[null],"warning":[null]},"changes":[],"dirtyIds":[]}],"databaseVersion":1.5,"engineVersion":1.5,"autosave":true,"autosaveInterval":5000,"autosaveHandle":null,"throttledSaves":true,"options":{"autosave":true,"autosaveInterval":5000,"serializationMethod":"normal","destructureDelimiter":"$<\n"},"persistenceMethod":"fs","persistenceAdapter":null,"verbose":false,"events":{"init":[null],"loaded":[],"flushChanges":[],"close":[],"changes":[],"warning":[]},"ENV":"NODEJS"}